{
    "insulin_sensitivity_factor": {
        "start_times": [
            "00:00:00",
            "14:00:00"
        ],
        "values": [
            35.71,
            25
        ]
    },
    "carb_insulin_ratio": {
        "start_times": [
            "00:00:00",
            "14:00:00"
        ],
        "values": [
            21.43,
            15
        ]
    },
    "basal_rate": {
        "start_times": [
            "00:00:00",
            "14:00:00"
        ],
        "values": [
            0.93,
            1.33
        ]
    },
    "glucose_sensitivity_factor": {
        "start_times": [
            "00:00:00"
        ],
        "values": [
            0.0007
        ]
    },
    "basal_blood_glucose": {
        "start_times": [
            "00:00:00"
        ],
        "values": [
            110.0
        ]
    },
    "insulin_production_rate": {
        "start_times": [
            "00:00:00"
        ],
        "values": [
            0.0
        ]
    }
}