{
  "metadata": {
    "risk-id": "TLR-969_3_5",
    "simulation_id": "TLR-969_3_5-base_resistant",
    "risk_description": "incorrect carb abs: 3h true, 5h select",
    "config_format_version": "v1.0"
  },
  "base_config": "reusable.simulations.base_resistant_autobolus",
  "override_config": [
    {"sim_id": "pre-Loop_NoMitigations_t1_resistant",
      "duration_hours": 23.0,
      "patient": {
        "patient_model": {
          "carb_entries": [
            {
              "start_time": "8/15/2019 12:00:00",
              "type": "carb",
              "duration": 180,
              "value": 31
            }
          ],
          "bolus_entries": "reusable.insulin_doses.accept_rec_v1"
        },
        "pump": {
          "carb_entries": [
            {
              "start_time": "8/15/2019 12:00:00",
              "type": "carb",
              "duration": 300,
              "value": 31
            }
          ]
        }
      }
    },
    {"sim_id": "pre-noLoop_t1_resistant",
      "duration_hours": 23.0,
      "patient": {
        "patient_model": {
          "carb_entries": [
            {
              "start_time": "8/15/2019 12:00:00",
              "type": "carb",
              "duration": 180,
              "value": 31
            }
          ],
          "bolus_entries": "reusable.insulin_doses.resistant_profile_v1"
        },
        "pump": {
          "carb_entries": [
            {
              "start_time": "8/15/2019 12:00:00",
              "type": "carb",
              "duration": 300,
              "value": 31
            }
          ],
          "bolus_entries": "reusable.insulin_doses.resistant_profile_v1"
        }
      }
    },
    {"sim_id": "post-Loop-WithMitigations_t1_resistant",
      "duration_hours": 23.0,
      "patient": {
        "patient_model": {
          "carb_entries": [
            {
              "start_time": "8/15/2019 12:00:00",
              "type": "carb",
              "duration": 180,
              "value": 31
            }
          ],
          "bolus_entries": "reusable.insulin_doses.accept_rec_v1"
        },
        "pump": {
          "carb_entries": [
            {
              "start_time": "8/15/2019 12:00:00",
              "type": "carb",
              "duration": 300,
              "value": 31
            }
          ],
          "target_range": "reusable.mitigations.guardrails.target_range_resistant_v1"
        }
      },
      "controller": {
        "settings": "reusable.mitigations.guardrails.controller_settings_resistant_swift"
      }
    }
]
}